AUTHORS
CHANGES
LICENSE
MANIFEST.in
README.rst
bootstrap.py
buildout.cfg
setup.cfg
setup.py
src/book/__init__.py
src/book.isbn.egg-info/PKG-INFO
src/book.isbn.egg-info/SOURCES.txt
src/book.isbn.egg-info/dependency_links.txt
src/book.isbn.egg-info/namespace_packages.txt
src/book.isbn.egg-info/not-zip-safe
src/book.isbn.egg-info/requires.txt
src/book.isbn.egg-info/top_level.txt
src/book/isbn/__init__.py
src/book/isbn/wsgi.py
src/book/isbn/wsgi_run.py
src/book/isbn/tests/test_isbn.py
src/book/isbn/tests/test_pep8.py