Metadata-Version: 1.0
Name: book.isbn
Version: 0.0.1
Summary: `book.isbn` is a package for book ISBN.
Home-page: http://pypi.python.org/pypi/book.isbn
Author: Tohru Ike
Author-email: tohru.ike@gmail.com
License: NEW BSD
Keywords: book
Platform: UNKNOWN
Classifier: Development Status :: 1 - Planning
Classifier: License :: OSI Approved :: BSD License
Classifier: Programming Language :: Python
Classifier: Topic :: Utilities
